swimlane_integration_testing/__init__.py
swimlane_integration_testing/conftest.py
swimlane_integration_testing/constants.py
swimlane_integration_testing/output_verify.py
swimlane_integration_testing/test_general_rest.py
swimlane_integration_testing-2.4.1.dist-info/licenses/LICENSE
swimlane_integration_testing-2.4.1.dist-info/METADATA
swimlane_integration_testing-2.4.1.dist-info/WHEEL
swimlane_integration_testing-2.4.1.dist-info/top_level.txt
swimlane_integration_testing-2.4.1.dist-info/RECORD
